codecanopy/__init__.py
codecanopy/cat.py
codecanopy/cli.py
codecanopy/config.py
codecanopy/tree.py
codecanopy/utils.py
codecanopy-0.1.1.dist-info/METADATA
codecanopy-0.1.1.dist-info/WHEEL
codecanopy-0.1.1.dist-info/entry_points.txt
codecanopy-0.1.1.dist-info/top_level.txt
codecanopy-0.1.1.dist-info/RECORD
